{
    "class": "Warrior",
    "level": 1,
    "xp": 60.0,
    "xp_required": 100.0,
    "hp": 46.3412671324775,
    "max_hp": 50,
    "stamina": 25,
    "max_stamina": 25,
    "gold": 27,
    "distance": 2,
    "cooldown_until": 1776193784.5360456,
    "stats": {
        "STR": 5,
        "DEX": 5,
        "CON": 5,
        "INT": 5,
        "WIS": 5,
        "DISPELL": 5
    },
    "skills": {
        "Lunge": {
            "level": 1,
            "xp": 9.78,
            "xp_required": 10.0
        },
        "Slash": {
            "level": 1,
            "xp": 9.76,
            "xp_required": 10.0
        },
        "Draw": {
            "level": 1,
            "xp": 9.6,
            "xp_required": 10.0
        },
        "Rage Slash": {
            "level": 1,
            "xp": 9.52,
            "xp_required": 10.0
        }
    }
}